LICENSE
README.md
pyproject.toml
setup.cfg
src/dnv_bladed_models/__init__.py
src/dnv_bladed_models/accelerometer.py
src/dnv_bladed_models/active_damper.py
src/dnv_bladed_models/actuator_response.py
src/dnv_bladed_models/actuator_response_insert.py
src/dnv_bladed_models/added_inertia.py
src/dnv_bladed_models/added_inertia_insert.py
src/dnv_bladed_models/additional_constrained_wave.py
src/dnv_bladed_models/aerodynamic_information_calculation.py
src/dnv_bladed_models/aerodynamic_model.py
src/dnv_bladed_models/aerodynamic_model_insert.py
src/dnv_bladed_models/aerodynamic_properties.py
src/dnv_bladed_models/aerodynamic_settings.py
src/dnv_bladed_models/aerofoil.py
src/dnv_bladed_models/aerofoil_library.py
src/dnv_bladed_models/aileron.py
src/dnv_bladed_models/aileron_aerofoil_library.py
src/dnv_bladed_models/air_characteristics.py
src/dnv_bladed_models/alpha_line.py
src/dnv_bladed_models/angle_range.py
src/dnv_bladed_models/angle_vs_stiffness_torque.py
src/dnv_bladed_models/applied_load.py
src/dnv_bladed_models/applied_load_insert.py
src/dnv_bladed_models/applied_moment_vs_friction_torque.py
src/dnv_bladed_models/applied_xy_force_vs_friction_torque.py
src/dnv_bladed_models/applied_z_force_vs_friction_torque.py
src/dnv_bladed_models/assembly.py
src/dnv_bladed_models/assembly_node.py
src/dnv_bladed_models/automatic_mac_camy_fuchs.py
src/dnv_bladed_models/automatic_simple_cutoff_frequency.py
src/dnv_bladed_models/beddoes_leishman_model.py
src/dnv_bladed_models/bending_torsion_coupling_terms_about_elastic_xy.py
src/dnv_bladed_models/blade.py
src/dnv_bladed_models/blade_additional_inertia.py
src/dnv_bladed_models/blade_aerodynamic_outputs.py
src/dnv_bladed_models/blade_element_momentum.py
src/dnv_bladed_models/blade_element_theory_corrections.py
src/dnv_bladed_models/blade_hydrodynamic_outputs.py
src/dnv_bladed_models/blade_load_outputs.py
src/dnv_bladed_models/blade_modelling.py
src/dnv_bladed_models/blade_modelling_insert.py
src/dnv_bladed_models/blade_motion_outputs.py
src/dnv_bladed_models.egg-info/PKG-INFO
src/dnv_bladed_models.egg-info/SOURCES.txt
src/dnv_bladed_models.egg-info/dependency_links.txt
src/dnv_bladed_models.egg-info/requires.txt
src/dnv_bladed_models.egg-info/top_level.txt