Metadata-Version: 2.4
Name: dnv_bladed_models
Version: 0.7.0
Summary: An API for working with Bladed Next Gen models.
Author: DNV
Author-email: DNV <bladednextgen@dnv.com>
License: MIT License
Project-URL: homepage, https://bladednextgen.dnv.com/
Keywords: bladed,models
Classifier: Operating System :: OS Independent
Classifier: Programming Language :: Python :: 3
Classifier: Programming Language :: Python :: 3.9
Requires-Python: >=3.9
License-File: LICENSE
Requires-Dist: pydantic==1.10.*
Dynamic: license-file
